gill/__init__.py
gill/aliases.py
gill/cli.py
gill/gill_chat.py
gill/gill_config.py
gill/gill_init.py
gill/gill_sysprompt.py
gill/help.py
gill/llm_api.py
gill/prompt_parser.py
gillmore-0.1.0.dist-info/licenses/LICENSE
gillmore-0.1.0.dist-info/METADATA
gillmore-0.1.0.dist-info/WHEEL
gillmore-0.1.0.dist-info/entry_points.txt
gillmore-0.1.0.dist-info/top_level.txt
gillmore-0.1.0.dist-info/RECORD
