Metadata-Version: 2.4
Name: gillmore
Version: 0.1.0
License-File: LICENSE
Requires-Dist: annotated-types==0.7.0
Requires-Dist: anyio==4.9.0
Requires-Dist: certifi==2025.7.14
Requires-Dist: distro==1.9.0
Requires-Dist: h11==0.16.0
Requires-Dist: httpcore==1.0.9
Requires-Dist: httpx==0.28.1
Requires-Dist: idna==3.10
Requires-Dist: jiter==0.10.0
Requires-Dist: openai==1.97.1
Requires-Dist: pydantic==2.11.7
Requires-Dist: pydantic_core==2.33.2
Requires-Dist: sniffio==1.3.1
Requires-Dist: toml==0.10.2
Requires-Dist: tqdm==4.67.1
Requires-Dist: typing-inspection==0.4.1
Requires-Dist: typing_extensions==4.14.1
Dynamic: license-file
Dynamic: requires-dist
